combinatorics_tb/__init__.py
combinatorics_tb/combinatorics.py
combinatorics_tb-0.0.1.dist-info/LICENSE
combinatorics_tb-0.0.1.dist-info/METADATA
combinatorics_tb-0.0.1.dist-info/WHEEL
combinatorics_tb-0.0.1.dist-info/top_level.txt
combinatorics_tb-0.0.1.dist-info/RECORD
