Metadata-Version: 2.1
Name: combinatorics_tb
Version: 0.0.1
Summary: A simple combinatorics package which offers combinations and permutations functions
Author-email: Thomas Brumbaugh <thomas.william.brumbaugh@gmail.com>
Project-URL: Homepage, https://github.com/pypa/combinatorics_tb
Project-URL: Issues, https://github.com/pypa/combinatorics_tb/issues
Classifier: Programming Language :: Python :: 3
Classifier: License :: OSI Approved :: MIT License
Classifier: Operating System :: OS Independent
Requires-Python: >=3.8
License-File: LICENSE
